HISTORY.md
MANIFEST.in
README.md
VERSION
requirements.txt
setup.py
gerbil/__init__.py
gerbil/gerbil.py
gerbil.egg-info/PKG-INFO
gerbil.egg-info/SOURCES.txt
gerbil.egg-info/dependency_links.txt
gerbil.egg-info/entry_points.txt
gerbil.egg-info/not-zip-safe
gerbil.egg-info/requires.txt
gerbil.egg-info/top_level.txt