Metadata-Version: 1.1
Name: gerbil
Version: 1.5.1
Summary: Tool for adding text to the bottom of PDF pages.
Home-page: https://github.com/bwghughes/gerbil
Author: Ben Hughes
Author-email: bwghughes@gmail.com
License: BSD
Keywords: gerbil
Platform: UNKNOWN
Classifier: Development Status :: 2 - Pre-Alpha
Classifier: Intended Audience :: Developers
Classifier: License :: OSI Approved :: BSD License
Classifier: Natural Language :: English
Classifier: Programming Language :: Python :: 3.4
